{
  "product": "uu_jokes_maing01",
  "version": "4.0.1",
  "license": "License Commercial",
  "description": {
    "en": "uuJokes is reference application for educational purposes",
    "cs": "uuJokes je referenční aplikace pro vzdělávací účely"
  },
  "devkit": {
    "development": {
      "appBoxLocationUri": "ues:UU-BT:PRD.UU-JOKESG01-NODEJS/APPBOX",
      "appDeploymentUri": "ues:EMF-BT[52816343470606949]:FAMILY_EM_DEV_RESOURCEPOOL_AWE[60378981f90380f4b78eef93]:UU.JOKES.MAING01[611f7600566164380e3891c4]"
    },
    "demo": {
      "appBoxLocationUri": "ues:UU-BT:PRD.UU-JOKESG01-NODEJS/APPBOX",
      "appDeploymentUri": "ues:NETPROV1-BT[99923616732505139]:B_PRODUCTION_EGL[632a26959d2f13ec54850721]:UU.JOKES.MAING01[635264073f824ed95d5a0e3c]"
    }
  },
  "uu_jokes_maing01-hi": {},
  "uu_jokes_maing01-server": {}
}
